callosum/__init__.py
callosum/abc.py
callosum/auth.py
callosum/compat.py
callosum/exceptions.py
callosum/io.py
callosum/ordering.py
callosum/py.typed
callosum/serial.py
callosum/serialize.py
callosum/lower/__init__.py
callosum/lower/dispatch_redis.py
callosum/lower/redis_common.py
callosum/lower/rpc_redis.py
callosum/lower/zeromq.py
callosum/pubsub/__init__.py
callosum/pubsub/channel.py
callosum/pubsub/message.py
callosum/pubsub/types.py
callosum/rpc/__init__.py
callosum/rpc/abc.py
callosum/rpc/channel.py
callosum/rpc/exceptions.py
callosum/rpc/message.py
callosum/rpc/types.py
callosum/upper/__init__.py
callosum/upper/thrift.py
callosum-1.0.3.dist-info/LICENSE
callosum-1.0.3.dist-info/METADATA
callosum-1.0.3.dist-info/WHEEL
callosum-1.0.3.dist-info/top_level.txt
callosum-1.0.3.dist-info/RECORD
