Metadata-Version: 2.1
Name: callosum
Version: 1.0.3
Summary: Callosum RPC Library
Download-URL: https://pypi.org/project/callosum
Author: Lablup Inc.
Author-email: devops@lablup.com
Maintainer: Joongi Kim
Maintainer-email: joongi@lablup.com
License: MIT
Project-URL: Homepage, https://github.com/lablup/callosum
Project-URL: Repository, https://github.com/lablup/callosum
Project-URL: Issues, https://github.com/lablup/callosum/issues
Project-URL: Changelog, https://github.com/lablup/callosum/blob/main/CHANGES.md
Keywords: asyncio,rpc,pubsub,messaging
Platform: POSIX
Classifier: Development Status :: 4 - Beta
Classifier: Framework :: AsyncIO
Classifier: License :: OSI Approved :: MIT License
Classifier: Intended Audience :: Developers
Classifier: Operating System :: POSIX
Classifier: Operating System :: MacOS :: MacOS X
Classifier: Programming Language :: Python :: 3
Classifier: Programming Language :: Python :: 3.11
Classifier: Topic :: Software Development
Classifier: Topic :: Software Development :: Libraries
Classifier: Topic :: Communications
Classifier: Topic :: Internet
Requires-Python: >=3.11
License-File: LICENSE
Requires-Dist: attrs >=21.3.0
Requires-Dist: python-dateutil >=2.8.2
Requires-Dist: msgpack >=1.0.7
Requires-Dist: temporenc >=0.1
Requires-Dist: yarl !=1.9.0,!=1.9.1,!=1.9.2,>=1.8.2
Provides-Extra: build
Requires-Dist: build >=1.0.3 ; extra == 'build'
Requires-Dist: wheel >=0.41.0 ; extra == 'build'
Requires-Dist: twine ~=4.0 ; extra == 'build'
Requires-Dist: towncrier ~=22.12 ; extra == 'build'
Provides-Extra: dev
Requires-Dist: pre-commit ; extra == 'dev'
Provides-Extra: docs
Requires-Dist: sphinx ~=4.3 ; extra == 'docs'
Requires-Dist: sphinx-autodoc-typehints ; extra == 'docs'
Provides-Extra: lint
Requires-Dist: ruff >=0.2.2 ; extra == 'lint'
Requires-Dist: ruff-lsp >=0.0.52 ; extra == 'lint'
Provides-Extra: redis
Requires-Dist: redis >=4.6.0 ; extra == 'redis'
Provides-Extra: snappy
Requires-Dist: python-snappy >=0.6.1 ; extra == 'snappy'
Provides-Extra: test
Requires-Dist: Click >=8.0 ; extra == 'test'
Requires-Dist: pytest ~=7.2.2 ; extra == 'test'
Requires-Dist: pytest-asyncio ~=0.21 ; extra == 'test'
Requires-Dist: pytest-cov >=4.0 ; extra == 'test'
Requires-Dist: pytest-mock >=3.10 ; extra == 'test'
Requires-Dist: codecov >=2.1 ; extra == 'test'
Provides-Extra: thrift
Requires-Dist: thriftpy2 >=0.4.20 ; extra == 'thrift'
Provides-Extra: typecheck
Requires-Dist: mypy ~=1.8.0 ; extra == 'typecheck'
Requires-Dist: types-python-dateutil ; extra == 'typecheck'
Provides-Extra: zeromq
Requires-Dist: pyzmq >=25.1.1 ; extra == 'zeromq'
